.gitignore
CHANGES.txt
MANIFEST.in
README.txt
bootstrap.py
buildout.cfg
setup.py
test-plone-3.3.x.cfg
test-plone-4.x.cfg
docs/INSTALL.txt
docs/LICENSE.GPL
docs/LICENSE.txt
src/collective/__init__.py
src/collective.virtualtreecategories.egg-info/PKG-INFO
src/collective.virtualtreecategories.egg-info/SOURCES.txt
src/collective.virtualtreecategories.egg-info/dependency_links.txt
src/collective.virtualtreecategories.egg-info/entry_points.txt
src/collective.virtualtreecategories.egg-info/namespace_packages.txt
src/collective.virtualtreecategories.egg-info/not-zip-safe
src/collective.virtualtreecategories.egg-info/requires.txt
src/collective.virtualtreecategories.egg-info/top_level.txt
src/collective/virtualtreecategories/README.txt
src/collective/virtualtreecategories/TODO.txt
src/collective/virtualtreecategories/__init__.py
src/collective/virtualtreecategories/config.py
src/collective/virtualtreecategories/configure.zcml
src/collective/virtualtreecategories/extender.py
src/collective/virtualtreecategories/interfaces.py
src/collective/virtualtreecategories/migration.py
src/collective/virtualtreecategories/setuphandlers.py
src/collective/virtualtreecategories/storage.py
src/collective/virtualtreecategories/testing.py
src/collective/virtualtreecategories/testing.zcml
src/collective/virtualtreecategories/usei18ndude.sh
src/collective/virtualtreecategories/widget.py
src/collective/virtualtreecategories/browser/__init__.py
src/collective/virtualtreecategories/browser/configure.zcml
src/collective/virtualtreecategories/browser/controlpanel.pt
src/collective/virtualtreecategories/browser/controlpanel.py
src/collective/virtualtreecategories/browser/interfaces.py
src/collective/virtualtreecategories/browser/jsTree/css.js
src/collective/virtualtreecategories/browser/jsTree/flat.xsl
src/collective/virtualtreecategories/browser/jsTree/jquery.cookie.js
src/collective/virtualtreecategories/browser/jsTree/jquery.hotkeys.js
src/collective/virtualtreecategories/browser/jsTree/jquery.listen.js
src/collective/virtualtreecategories/browser/jsTree/jquery.log.js
src/collective/virtualtreecategories/browser/jsTree/jquery.metadata.js
src/collective/virtualtreecategories/browser/jsTree/jquery.tree_component.js
src/collective/virtualtreecategories/browser/jsTree/jquery.xslt.js
src/collective/virtualtreecategories/browser/jsTree/nested.xsl
src/collective/virtualtreecategories/browser/jsTree/sarissa.js
src/collective/virtualtreecategories/browser/jsTree/sarissa_ieemu_xpath.js
