Metadata-Version: 1.0
Name: collective.virtualtreecategories
Version: 0.3.3
Summary: Virtual tree categories/keywords for Plone
Home-page: http://pypi.python.org/pypi/collective.virtualtreecategories
Author: Radim Novotny
Author-email: novotny.radim@gmail.com
License: GPL
Keywords: plone keywords categories
Platform: UNKNOWN
Classifier: Framework :: Plone
Classifier: Programming Language :: Python
Classifier: Topic :: Software Development :: Libraries :: Python Modules
